podman_compose.py
v_podman_compose-1.0.4b1.dist-info/LICENSE
v_podman_compose-1.0.4b1.dist-info/METADATA
v_podman_compose-1.0.4b1.dist-info/WHEEL
v_podman_compose-1.0.4b1.dist-info/entry_points.txt
v_podman_compose-1.0.4b1.dist-info/top_level.txt
v_podman_compose-1.0.4b1.dist-info/RECORD
