Metadata-Version: 2.1
Name: v-podman-compose
Version: 1.0.4b1
Summary: A script to run docker-compose.yml using podman
Home-page: https://github.com/vanutp/podman-compose
Author: Muayyad Alsadi
Author-email: alsadi@gmail.com
License: GPL-2.0-only
Keywords: podman,podman-compose
Platform: UNKNOWN
Classifier: Programming Language :: Python
Classifier: Programming Language :: Python :: 3
Classifier: Programming Language :: Python :: 3.5
Classifier: Programming Language :: Python :: 3.6
Classifier: Programming Language :: Python :: 3.7
Classifier: Intended Audience :: Developers
Classifier: Operating System :: OS Independent
Classifier: Development Status :: 3 - Alpha
Classifier: Topic :: Software Development :: Build Tools
Classifier: License :: OSI Approved :: GNU General Public License v2 (GPLv2)
License-File: LICENSE
Requires-Dist: pyyaml
Requires-Dist: python-dotenv
